<?xml version="1.0"?>
<?xml-stylesheet href="summary.xsl" type="text/xsl"?>
<summary>
  <element name="GLOBALS" shortname="GL" ord="1">
    <svalue name="VERSION">v2022.1.0.0.0</svalue>
    <svalue name="BUILD">Apr 27 2022 22:44:48</svalue>
    <svalue name="GIT_BUILD_HASH">7670062eda46b95e13935a621f250d93513addf7</svalue>
    <svalue name="SYSTEM">x86_64-unknown-winnt_i19v19</svalue>
    <svalue name="SIMULATION_MODE">simulation</svalue>
    <svalue name="SIMULATION_SUBMODE">BOOST</svalue>
    <svalue name="PROJECT">"4-Cylinder"</svalue>
    <svalue name="RUN">"WOT"</svalue>
    <svalue name="DATE">"7.3.2000"</svalue>
    <dvalue name="INPUT_CPU_TIME" unit="s">4.62400000</dvalue>
    <dvalue name="CALCULATION_CPU_TIME" unit="s">2.87900000</dvalue>
    <dvalue name="OUTPUT_CPU_TIME" unit="s">0.01600000</dvalue>
    <dvalue name="TOTAL_CPU_TIME" unit="s">7.51900000</dvalue>
    <dvalue name="REQUIRED_CPU_TIME" unit="s">2.07812500</dvalue>
    <dvalue name="INDICATED_TORQUE" unit="Nm">61.95593729</dvalue>
    <dvalue name="INDICATED_SPECIFIC_TORQUE" unit="Nm/l">124.02170468</dvalue>
    <dvalue name="INDICATED_POWER" unit="kW">38.92806349</dvalue>
    <dvalue name="INDICATED_POWER_PS" unit="PS">52.92743664</dvalue>
    <dvalue name="INDICATED_SPECIFIC_POWER" unit="kW/l">77.92513526</dvalue>
    <dvalue name="INDICATED_SPECIFIC_POWER_PS_l" unit="PS/l">105.94869844</dvalue>
    <dvalue name="FRICTION_TORQUE" unit="Nm">8.63218857</dvalue>
    <dvalue name="FRICTION_POWER" unit="kW">5.42376404</dvalue>
    <dvalue name="EFFECTIVE_TORQUE" unit="Nm">53.32374872</dvalue>
    <dvalue name="EFFECTIVE_SPECIFIC_TORQUE" unit="Nm/l">106.74202515</dvalue>
    <dvalue name="EFFECTIVE_POWER" unit="kW">33.50429945</dvalue>
    <dvalue name="EFFECTIVE_POWER_PS" unit="PS">45.55316981</dvalue>
    <dvalue name="EFFECTIVE_SPECIFIC_POWER" unit="kW/l">67.06799241</dvalue>
    <dvalue name="EFFECTIVE_SPECIFIC_POWER_PS_l" unit="PS/l">91.18709231</dvalue>
    <dvalue name="ENGINE_SPEED" unit="rpm">6000.00000000</dvalue>
    <dvalue name="CYCLE_DURATION" unit="degrees">720.00000000</dvalue>
    <dvalue name="CRANKANGLE_STEP" unit="degrees">1.30281302</dvalue>
    <dvalue name="TIME_STEP" unit="ms">0.03618925</dvalue>
    <ivalue name="CYCLES_CALCULATED">20</ivalue>
    <ivalue name="CONVERGED">0</ivalue>
  </element>
  <element name="PIPE" shortname="PI" ord="1">
    <ivalue name="CELLS">2</ivalue>
    <dvalue name="CELL_SIZE" unit="mm">40.00000000</dvalue>
    <dvalue name="WALL_HEAT_FLOW" unit="kJ">0.00097449</dvalue>
    <dvalue name="WALL_HEAT_FLOW_RATE" unit="kW">0.04872442</dvalue>
    <dvalue name="WALL_TEMPERATURE" unit="K">340.00000000</dvalue>
    <element_ref name="PIPE_END" position="INLET" ord="7"/>
    <element_ref name="PIPE_END" position="OUTLET" ord="3"/>
  </element>
  <element name="PIPE" shortname="PI" ord="2">
    <ivalue name="CELLS">2</ivalue>
    <dvalue name="CELL_SIZE" unit="mm">30.00000000</dvalue>
    <dvalue name="WALL_HEAT_FLOW" unit="kJ">-0.00710481</dvalue>
    <dvalue name="WALL_HEAT_FLOW_RATE" unit="kW">-0.35524065</dvalue>
    <dvalue name="WALL_TEMPERATURE" unit="K">850.00000000</dvalue>
    <element_ref name="PIPE_END" position="INLET" ord="4"/>
    <element_ref name="PIPE_END" position="OUTLET" ord="5"/>
  </element>
  <element name="PIPE" shortname="PI" ord="3">
    <ivalue name="CELLS">5</ivalue>
    <dvalue name="CELL_SIZE" unit="mm">33.98000000</dvalue>
    <dvalue name="WALL_HEAT_FLOW" unit="kJ">0.00079860</dvalue>
    <dvalue name="WALL_HEAT_FLOW_RATE" unit="kW">0.03993004</dvalue>
    <dvalue name="WALL_TEMPERATURE" unit="K">300.00000000</dvalue>
    <element_ref name="PIPE_END" position="INLET" ord="1"/>
    <element_ref name="PIPE_END" position="OUTLET" ord="8"/>
  </element>
  <element name="PIPE" shortname="PI" ord="4">
    <ivalue name="CELLS">15</ivalue>
    <dvalue name="CELL_SIZE" unit="mm">31.30666667</dvalue>
    <dvalue name="WALL_HEAT_FLOW" unit="kJ">-0.16390418</dvalue>
    <dvalue name="WALL_HEAT_FLOW_RATE" unit="kW">-8.19520917</dvalue>
    <dvalue name="WALL_TEMPERATURE" unit="K">300.00000000</dvalue>
    <element_ref name="PIPE_END" position="INLET" ord="6"/>
    <element_ref name="PIPE_END" position="OUTLET" ord="2"/>
  </element>
  <element name="MEASURINGPOINT" shortname="MP" ord="1">
    <dvalue name="LOCATION" unit="mm">10.00000000</dvalue>
    <dvalue name="PRESSURE" unit="Pa">97833.57537460</dvalue>
    <dvalue name="VELOCITY" unit="m/s">35.82610900</dvalue>
    <dvalue name="TEMPERATURE" unit="K">293.73652451</dvalue>
    <dvalue name="MASSFLOW" unit="kg/cycle">0.00065056</dvalue>
    <dvalue name="MASSFLOWPERS" unit="kg/s">0.03252786</dvalue>
    <dvalue name="MASSFLOWAVERAGED-TEMPERATURE" unit="K">282.42242323</dvalue>
    <dvalue name="MACHNUMBER" unit="-">0.10678408</dvalue>
    <dvalue name="STAGNATIONPRESSURE" unit="Pa">100882.87767375</dvalue>
    <dvalue name="STAGNATIONTEMPERATURE" unit="K">296.54414689</dvalue>
    <dvalue name="ENTHALPYFLOWPERS" unit="J/s">-145.71681122</dvalue>
    <dvalue name="REYNOLDSNUMBER" unit="-">91633.22227517</dvalue>
    <dvalue name="WALLTEMPERATURE" unit="K">340.00000000</dvalue>
    <dvalue name="CONVERGENCE" unit="-">0.00000000</dvalue>
    <dvalue name="DENSITY" unit="-">1.15268153</dvalue>
    <dvalue name="SPECHEATCP" unit="J/kgK">1006.70712524</dvalue>
    <dvalue name="ISENTROPIC-EXPONENT" unit="-">1.39895893</dvalue>
    <dvalue name="GAS-CONSTANT" unit="J/kgK">287.09533967</dvalue>
    <element_att name="PIPE" ord="1"/>
  </element>
  <element name="MEASURINGPOINT" shortname="MP" ord="2">
    <dvalue name="LOCATION" unit="mm">10.00000000</dvalue>
    <dvalue name="PRESSURE" unit="Pa">114815.62637711</dvalue>
    <dvalue name="VELOCITY" unit="m/s">99.15518887</dvalue>
    <dvalue name="TEMPERATURE" unit="K">1037.24691963</dvalue>
    <dvalue name="MASSFLOW" unit="kg/cycle">0.00069563</dvalue>
    <dvalue name="MASSFLOWPERS" unit="kg/s">0.03478133</dvalue>
    <dvalue name="MASSFLOWAVERAGED-TEMPERATURE" unit="K">1261.43011289</dvalue>
    <dvalue name="MACHNUMBER" unit="-">0.15006693</dvalue>
    <dvalue name="STAGNATIONPRESSURE" unit="Pa">123933.92285731</dvalue>
    <dvalue name="STAGNATIONTEMPERATURE" unit="K">1051.36173807</dvalue>
    <dvalue name="ENTHALPYFLOWPERS" unit="J/s">42718.46403180</dvalue>
    <dvalue name="REYNOLDSNUMBER" unit="-">33397.25175530</dvalue>
    <dvalue name="WALLTEMPERATURE" unit="K">300.00000000</dvalue>
    <dvalue name="CONVERGENCE" unit="-">0.00000000</dvalue>
    <dvalue name="DENSITY" unit="-">0.37948806</dvalue>
    <dvalue name="SPECHEATCP" unit="J/kgK">1261.60670244</dvalue>
    <dvalue name="ISENTROPIC-EXPONENT" unit="-">1.29218118</dvalue>
    <dvalue name="GAS-CONSTANT" unit="J/kgK">285.06477991</dvalue>
    <element_att name="PIPE" ord="4"/>
  </element>
  <element name="SYSTEMBOUNDARY" shortname="SB" ord="1">
    <element_ref name="PIPE_END" ord="1"/>
  </element>
  <element name="SYSTEMBOUNDARY" shortname="SB" ord="2">
    <element_ref name="PIPE_END" ord="2"/>
  </element>
  <element name="ENGINE" shortname="EN" ord="1">
    <dvalue name="DISPLACED_VOLUME" unit="l">0.49955721</dvalue>
    <dvalue name="ENDOFCYCLE-TIME" unit="s">0.40000000</dvalue>
    <dvalue name="CYCLEAVERAGEDSPEED" unit="rpm">6000.00000000</dvalue>
    <dvalue name="CYCLEFREQUENCY" unit="Hz">50.00000000</dvalue>
    <dvalue name="CYCLEPERIOD" unit="s">0.02000000</dvalue>
    <dvalue name="PRESSURE-AMB" unit="Pa">100000.00000000</dvalue>
    <dvalue name="TEMPERATURE-AMB" unit="K">298.00000000</dvalue>
    <dvalue name="A/F-RATIO-STOICH_SHP" unit="-">14.50000000</dvalue>
    <dvalue name="LOWER-HEAT-VALUE_C" unit="J/kg">0.435000000000E+08</dvalue>
    <dvalue name="NBR-OF-CYLINDERS_GEO" unit="-">1.00000000</dvalue>
    <dvalue name="ENGINE-DISPLACEMENT_GEO" unit="m3">0.00049956</dvalue>
    <dvalue name="IMEP_PF" unit="bar">15.58502705</dvalue>
    <dvalue name="BMEP_PF" unit="bar">13.41359848</dvalue>
    <dvalue name="FMEP_PF" unit="bar">2.17142857</dvalue>
    <dvalue name="AMEP_PF" unit="bar">0.00000000</dvalue>
    <dvalue name="TORQUE_PF" unit="Nm">53.32374872</dvalue>
    <dvalue name="POWER_PF" unit="kW">33.50429945</dvalue>
    <dvalue name="FRICTIONTORQUE_PF" unit="Nm">8.63218857</dvalue>
    <dvalue name="FRICTIONPOWER_PF" unit="kW">5.42376404</dvalue>
    <dvalue name="ISFC1_PF" unit="g/kWh">207.37338697</dvalue>
    <dvalue name="ISFC2_PF" unit="g/kWh">207.37338697</dvalue>
    <dvalue name="BSFC_PF" unit="g/kWh">240.94353580</dvalue>
    <dvalue name="IMEP-EX_PF" unit="bar">-1.37081336</dvalue>
    <dvalue name="IMEP-IN_PF" unit="bar">0.71796875</dvalue>
    <dvalue name="IMEP-GE_PF" unit="bar">-0.65284461</dvalue>
    <dvalue name="IMEP-HP_PF" unit="bar">16.23787167</dvalue>
    <dvalue name="DELIVERYRATIO-AMB_G" unit="-">1.11411272</dvalue>
    <dvalue name="DELIVERYRATIO-INT_G" unit="-">1.11411272</dvalue>
    <dvalue name="AIRDELIVERYRATIO-AMB_G" unit="-">1.11411276</dvalue>
    <dvalue name="AIRDELIVERYRATIO-INT_G" unit="-">1.11411276</dvalue>
    <dvalue name="VOLUMETRICEFFICIENCY-AMB_G" unit="-">1.11367302</dvalue>
    <dvalue name="VOLUMETRICEFFICIENCY-INT_G" unit="-">1.11367302</dvalue>
    <dvalue name="TRAPPED-FUEL_MB" unit="kg">0.00004485</dvalue>
    <dvalue name="MASS-ASPIRATED_MB" unit="kg">0.00065053</dvalue>
    <dvalue name="AIRMASS-ASPIRATED_MB" unit="kg">0.00065053</dvalue>
    <dvalue name="FUELMASS-ASPIRATED_MB" unit="kg">-0.00000000</dvalue>
    <dvalue name="MASS-ASPIRATED-PERS_MB" unit="kg/s">0.03252641</dvalue>
    <dvalue name="AIRMASS-ASPIRATED-PERS_MB" unit="kg/s">0.03252641</dvalue>
    <dvalue name="FUELMASS-ASPIRATED-PERS_MB" unit="kg/s">-0.00000000</dvalue>
    <dvalue name="FUEL-ENERGY_EB" unit="J">1951.86529872</dvalue>
    <dvalue name="FUEL-ENERGY-PERS_EB" unit="W">97593.26493591</dvalue>
    <dvalue name="RELEASED-ENERGY_EB" unit="J">1892.90395227</dvalue>
    <dvalue name="RELEASED-ENERGY-PERS_EB" unit="W">94645.19761348</dvalue>
    <dvalue name="GROSS-RELEASED-ENERGY_EB" unit="J">1892.90395227</dvalue>
    <dvalue name="EFF-RELEASED-ENERGY_EB" unit="J">1880.90163699</dvalue>
    <dvalue name="EFF-RELEASED-ENERGY-PERS_EB" unit="W">94045.08184936</dvalue>
    <dvalue name="EFF-GROSS-RELEASED-ENERGY_EB" unit="J">1880.90163699</dvalue>
    <dvalue name="ISO-VOL-COMB-EFFICIENCY_PF" unit="-">0.97859822</dvalue>
    <dvalue name="ENERGYBALANCE_EB" unit="-">0.99775583</dvalue>
    <dvalue name="EFFENERGYBALANCE_EB" unit="-">0.99142937</dvalue>
    <dvalue name="WALLHEATFLOW_H" unit="J/cycle">-233.16244507</dvalue>
    <dvalue name="WALLHEATFLOWPERS_H" unit="W">-11658.12225338</dvalue>
    <dvalue name="PISTONWALLHEATFLOW_H" unit="J/cycle">-69.43367228</dvalue>
    <dvalue name="HEADWALLHEATFLOW_H" unit="J/cycle">-82.91336960</dvalue>
    <dvalue name="LINERWALLHEATFLOW_H" unit="J/cycle">-80.81540318</dvalue>
    <dvalue name="PISTONTEMPERATURE_H" unit="K">560.00000000</dvalue>
    <dvalue name="HEADTEMPERATURE_H" unit="K">635.00000000</dvalue>
    <dvalue name="LINERTDCTEMPERATURE_H" unit="K">455.00000000</dvalue>
    <dvalue name="LINERBDCTEMPERATURE_H" unit="K">450.00000000</dvalue>
    <dvalue name="PEAKCYLINDERPRESSURE_C" unit="Pa">0.878188992970E+07</dvalue>
    <dvalue name="PEAKCYLINDERPRESSURE-CRANKANGLE_C" unit="deg">12.32448886</dvalue>
    <dvalue name="PEAKPRESSURERISE_C" unit="Pa/deg">470559.01551541</dvalue>
    <dvalue name="PEAKPRESSURERISE-CRANKANGLE_C" unit="deg">1.54056111</dvalue>
    <dvalue name="RES-GASCOMPRESS_C" unit="bar">0.71708653</dvalue>
    <dvalue name="RES-GASCOMPRESS-CRANKANGLE_C" unit="deg">360.00000000</dvalue>
    <dvalue name="RESIDUALGASMASSIN_MB" unit="kg">-0.00000000</dvalue>
    <dvalue name="RESIDUALGASMASSIN-PERS_MB" unit="kg/s">0.00000000</dvalue>
    <dvalue name="RESIDUALGASMASSINTOCYL_MB" unit="kg">0.00000000</dvalue>
    <dvalue name="RESIDUALGASMASSEX_MB" unit="kg">0.00069466</dvalue>
    <dvalue name="RESIDUALGASMASSEXTOCYL_MB" unit="kg">0.00000005</dvalue>
    <dvalue name="TOTALRESIDUALGAS-CONC_MB" unit="-">0.01966192</dvalue>
    <dvalue name="A/F-RATIO-UNBRND_SHP" unit="-">14.67159046</dvalue>
    <dvalue name="AIR-EXCESS-RATIO_SHP" unit="-">1.01183382</dvalue>
    <dvalue name="ACCUMULATEDNOX_M" unit="g/kWh">13.75462655</dvalue>
    <dvalue name="ACCUMULATEDCO_M" unit="g/kWh">0.93691709</dvalue>
    <dvalue name="ACCUMULATEDHC_M" unit="g/kWh">0.41001159</dvalue>
    <dvalue name="ACCUMULATEDNOX-TIME_M" unit="kg/s">0.00012801</dvalue>
    <dvalue name="ACCUMULATEDCO-TIME_M" unit="kg/s">0.00000872</dvalue>
    <dvalue name="ACCUMULATEDHC-TIME_M" unit="kg/s">0.00000382</dvalue>
    <dvalue name="ACCUMULATEDNOX-MOLEFRACTION_M" unit="-">0.00354859</dvalue>
    <dvalue name="ACCUMULATEDCO-MOLEFRACTION_M" unit="-">0.00025894</dvalue>
    <dvalue name="ACCUMULATEDHC-MOLEFRACTION_M" unit="-">0.00007557</dvalue>
    <dvalue name="ACCUMULATEDSOOT-TIME_M" unit="kg/s">0.00000000</dvalue>
    <dvalue name="OCTANENUMBER_C" unit="-">89.09287598</dvalue>
    <dvalue name="SWIRL_G" unit="-">0.00000000</dvalue>
    <dvalue name="BLOWBY_G" unit="kg/cycle">0.00000000</dvalue>
    <dvalue name="BLOWBYENTHALPYFLOW_EB" unit="J/cycle">0.00000000</dvalue>
    <dvalue name="EVAPORATIONENERGY_EB" unit="J/cycle">-13.18492218</dvalue>
    <dvalue name="COMPRESSIONRATIO_GEO" unit="-">10.50000000</dvalue>
    <dvalue name="ENTHALPYFLUX-IN_EB" unit="W">-103.46284489</dvalue>
    <dvalue name="ENTHALPYFLUX-EX_EB" unit="W">43240.79036922</dvalue>
    <dvalue name="PORTWALLHEATFLOW-IN_EB" unit="W">21.48340633</dvalue>
    <dvalue name="PORTWALLHEATFLOW-EX_EB" unit="W">-302.51066519</dvalue>
    <dvalue name="TRAPPED-FUEL-PERS_MB" unit="kg/s">0.00224240</dvalue>
    <dvalue name="COMBUSTIONSTART_C" unit="deg">-10.00000000</dvalue>
    <dvalue name="COMBUSTIONDURATION_C" unit="deg">38.00000000</dvalue>
    <dvalue name="PEAKCYLINDERTEMPERATURE" unit="K">2721.96434070</dvalue>
    <dvalue name="PEAKCYLINDERTEMPERATURE-CRANKANGLE" unit="deg">16.94617218</dvalue>
    <dvalue name="PEAKTEMPERATUREBURNEDZONE_C" unit="K">2818.41229167</dvalue>
    <dvalue name="PEAKTEMPERATUREBURNEDZONE-CRANKANGLE_C" unit="deg">9.24336664</dvalue>
    <dvalue name="FUELMASSINJECTED" unit="kg">0.00004485</dvalue>
    <dvalue name="MEAN-EFF-HTC_H" unit="W/(m^2.K)">647.42758759</dvalue>
    <dvalue name="MEAN-EFF-HTGASTEMP_H" unit="K">1475.27427075</dvalue>
    <dvalue name="CONVERGENCE" unit="-">0.00000000</dvalue>
    <dvalue name="ENTHALPYFLUX-FUEL_EB" unit="W">-889.37006962</dvalue>
    <dvalue name="INDICATED-EFFICIENCY_PF" unit="-">0.39908024</dvalue>
    <dvalue name="EFFECTIVE-EFFICIENCY_PF" unit="-">0.34347724</dvalue>
    <dvalue name="MECHANICAL-EFFICIENCY_PF" unit="-">0.86067213</dvalue>
    <dvalue name="BRAKE_POWER_PERCENT" unit="%">35.39989381</dvalue>
    <dvalue name="LOSS_FRICTION_PCENT" unit="%">5.73062784</dvalue>
    <dvalue name="LOSS_WHT_PISTON_PCENT" unit="%">3.66810330</dvalue>
    <dvalue name="LOSS_WHT_HEAD_PCENT" unit="%">4.38022064</dvalue>
    <dvalue name="LOSS_WHT_LINER_PCENT" unit="%">4.26938742</dvalue>
    <dvalue name="LOSS_WHT_INTAKE_PCENT" unit="%">-0.02269889</dvalue>
    <dvalue name="LOSS_WHT_EXHAUST_PCENT" unit="%">0.31962601</dvalue>
    <dvalue name="LOSS_EXH_GASES_PCENT" unit="%">45.79656898</dvalue>
    <dvalue name="DYNAMIC_COMPRESSION_RATIO" unit="-">8.52140119</dvalue>
    <dvalue name="FUEL_MASS_DELIVERED_RATE" unit="g/s">2.24240121</dvalue>
    <dvalue name="INTAKE_PORT_WALL_T" unit="K">360.00000000</dvalue>
    <dvalue name="EXHAUST_PORT_WALL_T" unit="K">585.00000000</dvalue>
  </element>
  <element name="CYLINDER" shortname="CY" ord="1">
    <dvalue name="BORE" unit="mm">86.00000000</dvalue>
    <dvalue name="STROKE" unit="mm">86.00000000</dvalue>
    <dvalue name="COMPRESSION_RATIO" unit="-">10.50000000</dvalue>
    <dvalue name="DYNAMIC_COMPRESSION_RATIO" unit="-">8.52140119</dvalue>
    <dvalue name="CONROD_LENGTH" unit="mm">143.50000000</dvalue>
    <dvalue name="CRANK_RADIUS" unit="mm">43.00000000</dvalue>
    <dvalue name="FIRING_TDC" unit="degrees">0.00000000</dvalue>
    <dvalue name="DISPLACED_VOLUME" unit="l">0.49955721</dvalue>
    <dvalue name="COMPRESSED_VOLUME" unit="l">0.05258497</dvalue>
    <dvalue name="PISTON_PIN_OFFSET" unit="mm">0.00000000</dvalue>
    <dvalue name="BLOWBY_GAP" unit="mm">0.00000000</dvalue>
    <dvalue name="CYLINDER-DISPLACEMENT" unit="m3">0.00049956</dvalue>
    <dvalue name="IMEP" unit="bar">15.58502705</dvalue>
    <dvalue name="BMEP" unit="bar">13.41359848</dvalue>
    <dvalue name="FMEP" unit="bar">2.17142857</dvalue>
    <dvalue name="ISFC1" unit="g/kWh">207.37338697</dvalue>
    <dvalue name="ISFC2" unit="g/kWh">207.37338697</dvalue>
    <dvalue name="BSFC" unit="g/kWh">240.94353580</dvalue>
    <dvalue name="IMEP-EX" unit="bar">-1.37081336</dvalue>
    <dvalue name="IMEP-IN" unit="bar">0.71796875</dvalue>
    <dvalue name="IMEP-GE" unit="bar">-0.65284461</dvalue>
    <dvalue name="HP-START-PRESSURE_SHP" unit="Pa">167015.13323771</dvalue>
    <dvalue name="HP-START-TEMPERATURE_SHP" unit="K">396.19177406</dvalue>
    <dvalue name="HP-START-TOTALMASS_SHP" unit="kg">0.00067069</dvalue>
    <dvalue name="HP-START-AIRMASS_SHP" unit="kg">0.00065027</dvalue>
    <dvalue name="TOTALRESIDUALGAS-CONC_SHP" unit="-">0.01966192</dvalue>
    <dvalue name="DELIVERYRATIO-AMB" unit="-">1.11411272</dvalue>
    <dvalue name="DELIVERYRATIO-INT" unit="-">1.11411272</dvalue>
    <dvalue name="AIRDELIVERYRATIO-AMB" unit="-">1.11411276</dvalue>
    <dvalue name="VOLUMETRICEFFICIENCY-AMB" unit="-">1.11367302</dvalue>
    <dvalue name="VOLUMETRICEFFICIENCY-INT" unit="-">1.11367302</dvalue>
    <dvalue name="A/F-RATIO-UNBRND_SHP" unit="-">14.67159046</dvalue>
    <dvalue name="A/F-RATIO-BRND_SHP" unit="-">14.51450803</dvalue>
    <dvalue name="AIR-EXCESS-RATIO_SHP" unit="-">1.01183382</dvalue>
    <dvalue name="TOTALFUELMASS" unit="kg">0.00004485</dvalue>
    <dvalue name="FUELMASSINJECTED" unit="kg">0.00004485</dvalue>
    <dvalue name="FUELMASS-ASPIRATED" unit="kg">0.00000000</dvalue>
    <dvalue name="RESIDUALGASMASSIN_G" unit="kg">-0.00000000</dvalue>
    <dvalue name="RESIDUALGASMASSINTOCYL_G" unit="kg">0.00000000</dvalue>
    <dvalue name="RESIDUALGASMASSEX_G" unit="kg">0.00069466</dvalue>
    <dvalue name="RESIDUALGASMASSEXTOCYL_G" unit="kg">0.00000005</dvalue>
    <dvalue name="WALLHEATFLOW_H" unit="J/cycle">-233.16244507</dvalue>
    <dvalue name="PISTONWALLHEATFLOW_H" unit="J/cycle">-69.43367228</dvalue>
    <dvalue name="HEADWALLHEATFLOW_H" unit="J/cycle">-82.91336960</dvalue>
    <dvalue name="LINERWALLHEATFLOW_H" unit="J/cycle">-80.81540318</dvalue>
    <dvalue name="PISTONTEMPERATURE_H" unit="K">560.00000000</dvalue>
    <dvalue name="HEADTEMPERATURE_H" unit="K">635.00000000</dvalue>
    <dvalue name="LINERTDCTEMPERATURE_H" unit="K">455.00000000</dvalue>
    <dvalue name="LINERBDCTEMPERATURE_H" unit="K">450.00000000</dvalue>
    <dvalue name="MEAN-EFF-HTC_H" unit="W/(m^2.K)">647.42758759</dvalue>
    <dvalue name="MEAN-EFF-HTGASTEMP_H" unit="K">1475.27427075</dvalue>
    <dvalue name="PEAKCYLINDERPRESSURE" unit="Pa">0.878188992970E+07</dvalue>
    <dvalue name="PEAKCYLINDERPRESSURE-CRANKANGLE" unit="deg">12.32448886</dvalue>
    <dvalue name="PEAKCYLINDERTEMPERATURE" unit="K">2721.96434070</dvalue>
    <dvalue name="PEAKCYLINDERTEMPERATURE-CRANKANGLE" unit="deg">16.94617218</dvalue>
    <dvalue name="PEAKPRESSURERISE" unit="Pa/deg">470559.01551541</dvalue>
    <dvalue name="PEAKPRESSURERISE-CRANKANGLE" unit="deg">1.54056111</dvalue>
    <dvalue name="RES-GASCOMPRESS" unit="bar">0.71708653</dvalue>
    <dvalue name="RES-GASCOMPRESS-CRANKANGLE" unit="deg">360.00000000</dvalue>
    <dvalue name="BLOWBY_G" unit="kg/cycle">0.00000000</dvalue>
    <dvalue name="BLOWBYENTHALPYFLOW_H" unit="J/cycle">0.00000000</dvalue>
    <dvalue name="AIRDELIVERYRATIO-INT" unit="-">1.11411276</dvalue>
    <dvalue name="COMBUSTIONSTART_C" unit="deg">-10.00000000</dvalue>
    <dvalue name="COMBUSTIONDURATION_C" unit="deg">38.00000000</dvalue>
    <dvalue name="PEAKTEMPERATUREBURNEDZONE_C" unit="K">2818.41229167</dvalue>
    <dvalue name="PEAKTEMPERATUREBURNEDZONE-CRANKANGLE_C" unit="deg">9.24336664</dvalue>
    <dvalue name="ACCUMULATEDNOX_M" unit="g/kWh">13.75462655</dvalue>
    <dvalue name="ACCUMULATEDCO_M" unit="g/kWh">0.93691709</dvalue>
    <dvalue name="ACCUMULATEDHC_M" unit="g/kWh">0.41001159</dvalue>
    <dvalue name="ACCUMULATEDNOX-TIME_M" unit="kg/s">0.00012801</dvalue>
    <dvalue name="ACCUMULATEDCO-TIME_M" unit="kg/s">0.00000872</dvalue>
    <dvalue name="ACCUMULATEDHC-TIME_M" unit="kg/s">0.00000382</dvalue>
    <dvalue name="ACCUMULATEDNOX-MOLEFRACTION_M" unit="-">0.00354859</dvalue>
    <dvalue name="ACCUMULATEDCO-MOLEFRACTION_M" unit="-">0.00025894</dvalue>
    <dvalue name="ACCUMULATEDHC-MOLEFRACTION_M" unit="-">0.00007557</dvalue>
    <dvalue name="OCTANENUMBER_C" unit="-">89.09287598</dvalue>
    <dvalue name="MASS-FRAC-BURNED-02-CRANKANGLE_C" unit="deg">-7.17077161</dvalue>
    <dvalue name="MASS-FRAC-BURNED-05-CRANKANGLE_C" unit="deg">-5.70553879</dvalue>
    <dvalue name="MASS-FRAC-BURNED-10-CRANKANGLE_C" unit="deg">-4.08265905</dvalue>
    <dvalue name="MASS-FRAC-BURNED-50-CRANKANGLE_C" unit="deg">3.69108899</dvalue>
    <dvalue name="MASS-FRAC-BURNED-90-CRANKANGLE_C" unit="deg">13.37610954</dvalue>
    <dvalue name="MASS-FRAC-BURNED-95-CRANKANGLE_C" unit="deg">16.28879426</dvalue>
    <dvalue name="EVAPORATIONENERGY_C" unit="J/cycle">-13.18492218</dvalue>
    <dvalue name="SOC-TEMPERATURE_C" unit="K">745.87508706</dvalue>
    <dvalue name="HP-START-FBMASS_SHP" unit="kg">0.00000085</dvalue>
    <dvalue name="ENTHALPYFLUX-FUEL" unit="J/cycle">-17.78740139</dvalue>
    <dvalue name="INDICATED-EFFICIENCY_PF" unit="-">0.39908024</dvalue>
    <dvalue name="EFFECTIVE-EFFICIENCY_PF" unit="-">0.34347724</dvalue>
    <dvalue name="SOC-PRESSURE_C" unit="Pa">0.249588900332E+07</dvalue>
    <dvalue name="BRAKE_POWER_PERCENT" unit="%">35.39989381</dvalue>
    <dvalue name="LOSS_FRICTION_PCENT" unit="%">5.73062784</dvalue>
    <dvalue name="LOSS_WHT_PISTON_PCENT" unit="%">3.66810330</dvalue>
    <dvalue name="LOSS_WHT_HEAD_PCENT" unit="%">4.38022064</dvalue>
    <dvalue name="LOSS_WHT_LINER_PCENT" unit="%">4.26938742</dvalue>
    <dvalue name="LOSS_WHT_INTAKE_PCENT" unit="%">-0.02269889</dvalue>
    <dvalue name="LOSS_WHT_EXHAUST_PCENT" unit="%">0.31962601</dvalue>
    <dvalue name="LOSS_EXH_GASES_PCENT" unit="%">45.79656898</dvalue>
    <element_ref name="PORT" position="INTAKE" ord="1"/>
    <element_ref name="PORT" position="EXHAUST" ord="2"/>
  </element>
  <element name="PORT" shortname="PO" ord="1">
    <svalue name="TYPE">INTAKE</svalue>
    <dvalue name="PORTWALLTEMPERATURE" unit="K">360.00000000</dvalue>
    <dvalue name="PORTWALLHEAT" unit="J/cycle">0.42966813</dvalue>
    <dvalue name="VALVEPORTOPENING-CLR0MM-CRANKANGLE" unit="deg">341.99936494</dvalue>
    <dvalue name="VALVEPORTOPENING-EFF0MM-CRANKANGLE" unit="deg">341.99936494</dvalue>
    <dvalue name="VALVEPORTOPENING-EFF1MM-CRANKANGLE" unit="deg">364.46070672</dvalue>
    <dvalue name="VALVEPORTOPENING-UDEFMM-CRANKANGLE" unit="deg">341.99936494</dvalue>
    <dvalue name="VALVEPORTCLOSING-CLR0MM-CRANKANGLE" unit="deg">601.99976569</dvalue>
    <dvalue name="VALVEPORTCLOSING-EFF0MM-CRANKANGLE" unit="deg">601.99976569</dvalue>
    <dvalue name="VALVEPORTCLOSING-EFF1MM-CRANKANGLE" unit="deg">569.67205371</dvalue>
    <dvalue name="VALVEPORTCLOSING-UDEFMM-CRANKANGLE" unit="deg">601.99976569</dvalue>
    <dvalue name="CAMPHASING" unit="deg">0.00000000</dvalue>
    <element_ref name="PIPE_END" ord="3"/>
  </element>
  <element name="PORT" shortname="PO" ord="2">
    <svalue name="TYPE">EXHAUST</svalue>
    <dvalue name="PORTWALLTEMPERATURE" unit="K">585.00000000</dvalue>
    <dvalue name="PORTWALLHEAT" unit="J/cycle">-6.05021330</dvalue>
    <dvalue name="VALVEPORTOPENING-CLR0MM-CRANKANGLE" unit="deg">122.00134488</dvalue>
    <dvalue name="VALVEPORTOPENING-EFF0MM-CRANKANGLE" unit="deg">122.00134488</dvalue>
    <dvalue name="VALVEPORTOPENING-EFF1MM-CRANKANGLE" unit="deg">142.84123026</dvalue>
    <dvalue name="VALVEPORTOPENING-UDEFMM-CRANKANGLE" unit="deg">122.00134488</dvalue>
    <dvalue name="VALVEPORTCLOSING-CLR0MM-CRANKANGLE" unit="deg">382.00122890</dvalue>
    <dvalue name="VALVEPORTCLOSING-EFF0MM-CRANKANGLE" unit="deg">382.00122890</dvalue>
    <dvalue name="VALVEPORTCLOSING-EFF1MM-CRANKANGLE" unit="deg">348.00011240</dvalue>
    <dvalue name="VALVEPORTCLOSING-UDEFMM-CRANKANGLE" unit="deg">382.00122890</dvalue>
    <dvalue name="CAMPHASING" unit="deg">0.00000000</dvalue>
    <element_ref name="PIPE_END" ord="4"/>
  </element>
  <element name="RESTRICTION" shortname="FR" ord="1">
    <element_ref name="PIPE_END" ord="5"/>
    <element_ref name="PIPE_END" ord="6"/>
  </element>
  <element name="RESTRICTION" shortname="FR" ord="2">
    <element_ref name="PIPE_END" ord="7"/>
    <element_ref name="PIPE_END" ord="8"/>
  </element>
  <element name="PIPE_END" shortname="PE" ord="1">
    <dvalue name="FLOWCOEFFICIENT" unit="-">1.00000000</dvalue>
    <dvalue name="MASSFLOW" unit="kg/cycle">0.00065037</dvalue>
    <dvalue name="VELOCITY" unit="m/s">36.26061903</dvalue>
    <element_att name="PIPE" ord="3"/>
    <element_att name="SYSTEMBOUNDARY" ord="1"/>
  </element>
  <element name="PIPE_END" shortname="PE" ord="2">
    <dvalue name="FLOWCOEFFICIENT" unit="-">1.00000000</dvalue>
    <dvalue name="MASSFLOW" unit="kg/cycle">0.00069545</dvalue>
    <dvalue name="VELOCITY" unit="m/s">103.77189876</dvalue>
    <element_att name="PIPE" ord="4"/>
    <element_att name="SYSTEMBOUNDARY" ord="2"/>
  </element>
  <element name="PIPE_END" shortname="PE" ord="3">
    <dvalue name="FLOWCOEFFICIENT" unit="-">0.22411465</dvalue>
    <dvalue name="MASSFLOW" unit="kg/cycle">0.00065053</dvalue>
    <dvalue name="VELOCITY" unit="m/s">36.41023051</dvalue>
    <element_att name="PIPE" ord="1"/>
    <element_att name="CYLINDER" ord="1"/>
  </element>
  <element name="PIPE_END" shortname="PE" ord="4">
    <dvalue name="FLOWCOEFFICIENT" unit="-">0.21904941</dvalue>
    <dvalue name="MASSFLOW" unit="kg/cycle">0.00069537</dvalue>
    <dvalue name="VELOCITY" unit="m/s">94.87622667</dvalue>
    <element_att name="PIPE" ord="2"/>
    <element_att name="CYLINDER" ord="1"/>
  </element>
  <element name="PIPE_END" shortname="PE" ord="5">
    <dvalue name="FLOWCOEFFICIENT" unit="-">0.95000000</dvalue>
    <dvalue name="MASSFLOW" unit="kg/cycle">0.00069537</dvalue>
    <dvalue name="VELOCITY" unit="m/s">96.41666283</dvalue>
    <element_att name="PIPE" ord="2"/>
    <element_att name="RESTRICTION" ord="1"/>
  </element>
  <element name="PIPE_END" shortname="PE" ord="6">
    <dvalue name="FLOWCOEFFICIENT" unit="-">0.95000000</dvalue>
    <dvalue name="MASSFLOW" unit="kg/cycle">0.00069545</dvalue>
    <dvalue name="VELOCITY" unit="m/s">99.26862275</dvalue>
    <element_att name="PIPE" ord="4"/>
    <element_att name="RESTRICTION" ord="1"/>
  </element>
  <element name="PIPE_END" shortname="PE" ord="7">
    <dvalue name="FLOWCOEFFICIENT" unit="-">0.98875027</dvalue>
    <dvalue name="MASSFLOW" unit="kg/cycle">0.00065053</dvalue>
    <dvalue name="VELOCITY" unit="m/s">35.71760323</dvalue>
    <element_att name="PIPE" ord="1"/>
    <element_att name="RESTRICTION" ord="2"/>
  </element>
  <element name="PIPE_END" shortname="PE" ord="8">
    <dvalue name="FLOWCOEFFICIENT" unit="-">1.01884130</dvalue>
    <dvalue name="MASSFLOW" unit="kg/cycle">0.00065037</dvalue>
    <dvalue name="VELOCITY" unit="m/s">37.15244373</dvalue>
    <element_att name="PIPE" ord="3"/>
    <element_att name="RESTRICTION" ord="2"/>
  </element>
</summary>
